LICENSE
README.md
setup.py
linkedin_scraper_in/__init__.py
linkedin_scraper_in.egg-info/PKG-INFO
linkedin_scraper_in.egg-info/SOURCES.txt
linkedin_scraper_in.egg-info/dependency_links.txt
linkedin_scraper_in.egg-info/requires.txt
linkedin_scraper_in.egg-info/top_level.txt