Metadata-Version: 2.1
Name: linkedin-scraper-in
Version: 1.0.4
Summary: A python library to scrape linkedin search results
Home-page: UNKNOWN
Author: DataKund
Author-email: datakund@gmail.com
License: Apache License 2.0
Keywords: linkedin search learning results python bot_studio automation search scraper scrape
Platform: UNKNOWN
License-File: LICENSE
